{
    "version": "2024-10-20-2356",
    "description": "Roguelike in a post-apocalyptic world (with sprite-based graphics, experimental build)",
    "homepage": "https://cataclysmdda.org",
    "license": "CC-BY-SA-3.0",
    "architecture": {
        "64bit": {
            "url": "https://github.com/CleverRaven/Cataclysm-DDA/releases/download/cdda-experimental-2024-10-20-2356/cdda-windows-tiles-x64-2024-10-20-2356.zip",
            "hash": "27dc061ae3f59bc0e7da84b2db0d432e98e9bc8a30c590e4aeee5dd18bae7886"
        }
    },
    "shortcuts": [
        [
            "cataclysm-tiles.exe",
            "Cataclysm DDA\\Cataclysm DDA Tiles (Experimental)"
        ]
    ],
    "persist": [
        "config",
        "save",
        "sound",
        "templates"
    ],
    "checkver": {
        "url": "https://github.com/CleverRaven/Cataclysm-DDA/releases/",
        "re": "Cataclysm-DDA experimental build ([\\d.-]+)"
    },
    "autoupdate": {
        "architecture": {
            "64bit": {
                "url": "https://github.com/CleverRaven/Cataclysm-DDA/releases/download/cdda-experimental-$version/cdda-windows-tiles-x64-$version.zip"
            }
        }
    }
}
